gravityfalls_ciphers/__init__.py
gravityfalls_ciphers/main.py
gravityfalls_ciphers-0.0.2.dist-info/METADATA
gravityfalls_ciphers-0.0.2.dist-info/WHEEL
gravityfalls_ciphers-0.0.2.dist-info/top_level.txt
gravityfalls_ciphers-0.0.2.dist-info/RECORD
