Metadata-Version: 2.4
Name: gravityfalls_ciphers
Version: 0.0.2
Dynamic: description
Dynamic: description-content-type
